ruvdsdriver/__init__.py
ruvdsdriver-0.0.1.dist-info/LICENSE
ruvdsdriver-0.0.1.dist-info/METADATA
ruvdsdriver-0.0.1.dist-info/WHEEL
ruvdsdriver-0.0.1.dist-info/top_level.txt
ruvdsdriver-0.0.1.dist-info/RECORD
