Metadata-Version: 2.1
Name: ruvdsdriver
Version: 0.0.1
Summary: Libcloud driver for RU VDS
Home-page: https://github.com/thebits/libcloud-ruvds
Author: Sergey Mezentsev
Author-email: thebits@yandex.ru
License: UNLICENSE
Classifier: Intended Audience :: System Administrators
Classifier: Operating System :: OS Independent
Classifier: Programming Language :: Python :: 3
License-File: LICENSE
Requires-Dist: apache-libcloud (>=3.0.0)
